[
    {
        "names": [
            "Truth & Love",
            "丘與樂樂團"
        ],
        "image_name": "-",
        "reference": "丘與樂樂團 article, source: Wikipedia",
        "article_url": "https://zh.wikipedia.org/wiki/%E4%B8%98%E8%88%87%E6%A8%82%E6%A8%82%E5%9C%98",
        "image_url": "-",
        "cc": "-"
    },
    {
        "names": [
            "Yeemao",
            "夜貓組"
        ],
        "image_name": "-",
        "reference": "夜貓組 article, source: Wikipedia",
        "article_url": "https://zh.wikipedia.org/wiki/%E5%A4%9C%E8%B2%93%E7%B5%84",
        "image_url": "-",
        "cc": "-"
    },
    {
        "names": [
            "草屯囝仔",
            "Caotun Boyz"
        ],
        "image_name": "-",
        "reference": "草屯囝仔 article, source: Wikipedia",
        "article_url": "https://zh.wikipedia.org/wiki/%E8%8D%89%E5%B1%AF%E5%9B%9D%E4%BB%94",
        "image_url": "-",
        "cc": "-"
    },
    {
        "names": [
            "臭屁嬰仔",
            "Cocky Boyz"
        ],
        "image_name": "-",
        "reference": "臭屁嬰仔 article, source: Wikipedia",
        "article_url": "https://zh.wikipedia.org/wiki/%E8%87%AD%E5%B1%81%E5%AC%B0%E4%BB%94",
        "image_url": "-",
        "cc": "-"
    },
    {
        "names": [
            "Kou Chou Ching",
            "拷秋勤"
        ],
        "image_name": "-",
        "reference": "拷秋勤 article, source: Wikipedia",
        "article_url": "https://zh.wikipedia.org/wiki/%E6%8B%B7%E7%A7%8B%E5%8B%A4",
        "image_url": "-",
        "cc": "-"
    },
    {
        "names": [
            "潘瑋柏",
            "Wilber Pan / Will Pan"
        ],
        "image_name": "潘瑋柏.png",
        "reference": "This image is provided by WebTVAsia Taiwan, 潘瑋柏 article, source: Wikipedia",
        "article_url": "https://zh.wikipedia.org/wiki/%E6%BD%98%E7%91%8B%E6%9F%8F",
        "image_url": "https://zh.wikipedia.org/wiki/%E6%BD%98%E7%91%8B%E6%9F%8F#/media/File:Will_Pan_Feb_7,_2017.jpg",
        "cc": "CC BY 3.0"
    },
    {
        "names": [
            "陳德修",
            "SHU"
        ],
        "image_name": "-",
        "reference": "陳德修 article, source: Wikipedia",
        "article_url": "https://zh.wikipedia.org/wiki/%E9%99%B3%E5%BE%B7%E4%BF%AE",
        "image_url": "-",
        "cc": "-"
    },
    {
        "names": [
            "謝和弦"
        ],
        "image_name": "謝和弦.png",
        "reference": "This image is provided by Onlymyself65536, 謝和弦 article, source: Wikipedia",
        "article_url": "https://zh.wikipedia.org/wiki/%E8%AC%9D%E5%92%8C%E5%BC%A6",
        "image_url": "https://zh.wikipedia.org/wiki/%E8%AC%9D%E5%92%8C%E5%BC%A6#/media/File:%E8%AC%9D%E5%92%8C%E5%BC%A6_%E5%8F%B0%E5%8D%97%E7%B0%BD%E5%94%B1%E6%9C%83_20110604.jpg",
        "cc": "CC BY-SA 3.0"
    },
    {
        "names": [
            "呂思緯",
            "鼓鼓",
            "GBOYSWAG"
        ],
        "image_name": "呂思緯.png",
        "reference": "This image is provided by 臺北捷運, 呂思緯 article, source: Wikipedia",
        "article_url": "https://zh.wikipedia.org/wiki/%E5%91%82%E6%80%9D%E7%B7%AF",
        "image_url": "https://zh.wikipedia.org/wiki/%E5%91%82%E6%80%9D%E7%B7%AF#/media/File:2023%E6%8D%B7%E9%81%8B%E7%9B%83%E8%A1%97%E8%88%9E%E5%A4%A7%E8%B3%BD%E4%BB%A3%E8%A8%80%E4%BA%BA_%E9%BC%93%E9%BC%93.jpg",
        "cc": "Attribution"
    },
    {
        "names": [
            "廖亦崟",
            "William"
        ],
        "image_name": "廖亦崟.png",
        "reference": "This image is provided by Lesterchong1993, 廖亦崟 article, source: Wikipedia",
        "article_url": "https://zh.wikipedia.org/wiki/%E5%BB%96%E4%BA%A6%E5%B4%9F",
        "image_url": "https://zh.wikipedia.org/wiki/%E5%BB%96%E4%BA%A6%E5%B4%9F#/media/File:LOLLIPOP_F%E5%A8%81%E5%BB%89.jpg",
        "cc": "CC BY-SA 3.0"
    },
    {
        "names": [
            "Brian",
            "Lil Jay",
            "廖允杰",
            "Jaydaone"
        ],
        "image_name": "-",
        "reference": "廖允杰 article, source: Wikipedia",
        "article_url": "https://zh.wikipedia.org/wiki/%E5%BB%96%E5%85%81%E6%9D%B0",
        "image_url": "-",
        "cc": "-"
    },
    {
        "names": [
            "Li Bo-En",
            "李伯恩"
        ],
        "image_name": "李伯恩.png",
        "reference": "This image is provided by Onlymyself65536, 李伯恩 article, source: Wikipedia",
        "article_url": "https://zh.wikipedia.org/wiki/%E6%9D%8E%E4%BC%AF%E6%81%A9",
        "image_url": "https://zh.wikipedia.org/wiki/%E6%9D%8E%E4%BC%AF%E6%81%A9#/media/File:%E8%87%AA%E7%94%B1%E7%99%BC%E6%8F%AE.JPG",
        "cc": "CC BY-SA 4.0"
    },
    {
        "names": [
            "Gummy B"
        ],
        "image_name": "-",
        "reference": "Gummy B article, source: Wikipedia",
        "article_url": "https://zh.wikipedia.org/wiki/Gummy_B",
        "image_url": "-",
        "cc": "-"
    },
    {
        "names": [
            "ADA",
            "昌璟翔"
        ],
        "image_name": "-",
        "reference": "昌璟翔 article, source: Wikipedia",
        "article_url": "https://zh.wikipedia.org/wiki/%E6%98%8C%E7%92%9F%E7%BF%94",
        "image_url": "-",
        "cc": "-"
    },
    {
        "names": [
            "田恩沛",
            "Tien En-Pei"
        ],
        "image_name": "-",
        "reference": "田恩沛 article, source: Wikipedia",
        "article_url": "https://zh.wikipedia.org/wiki/%E7%94%B0%E6%81%A9%E6%B2%9B",
        "image_url": "-",
        "cc": "-"
    },
    {
        "names": [
            "艾成"
        ],
        "image_name": "艾成.png",
        "reference": "This image is provided by Eva77622, 艾成 article, source: Wikipedia",
        "article_url": "https://zh.wikipedia.org/wiki/%E8%89%BE%E6%88%90",
        "image_url": "https://zh.wikipedia.org/wiki/%E8%89%BE%E6%88%90#/media/File:Eison_Cai_from_Super_Idol_20081213.jpg",
        "cc": "公有領域"
    },
    {
        "names": [
            "艾力克斯",
            "Alex Niu"
        ],
        "image_name": "艾力克斯.png",
        "reference": "This image is provided by 邱鈺鋒, 艾力克斯 article, source: Wikipedia",
        "article_url": "https://zh.wikipedia.org/wiki/%E8%89%BE%E5%8A%9B%E5%85%8B%E6%96%AF_(%E8%97%9D%E4%BA%BA)",
        "image_url": "https://zh.wikipedia.org/wiki/%E8%89%BE%E5%8A%9B%E5%85%8B%E6%96%AF_(%E8%97%9D%E4%BA%BA)#/media/File:Alex_Niu_at_Diablo_III_event_20120514.jpg",
        "cc": "CC BY-SA 4.0"
    },
    {
        "names": [
            "安鈞璨",
            "Shone An"
        ],
        "image_name": "安鈞璨.png",
        "reference": "This image is provided by -, 安鈞璨 article, source: Wikipedia",
        "article_url": "https://zh.wikipedia.org/wiki/%E5%AE%89%E9%88%9E%E7%92%A8",
        "image_url": "https://zh.wikipedia.org/wiki/%E5%AE%89%E9%88%9E%E7%92%A8#/media/File:%E5%AE%89%E9%88%9E%E7%92%A8.JPG",
        "cc": "合理使用"
    },
    {
        "names": [
            "童立安",
            "Andy Tung"
        ],
        "image_name": "童立安.png",
        "reference": "This image is provided by AnnE Lin, 童立安 article, source: Wikipedia",
        "article_url": "https://zh.wikipedia.org/wiki/%E7%AB%A5%E7%AB%8B%E5%AE%89",
        "image_url": "https://zh.wikipedia.org/wiki/%E7%AB%A5%E7%AB%8B%E5%AE%89#/media/File:%E6%94%9D%E6%96%BC2015%E5%B9%B48%E6%9C%889%E6%97%A5_%E7%AB%A5%E6%A8%82%E6%9C%83%EF%BC%8D%E5%B0%8F%E5%AE%89%E5%A4%8F%E6%97%A5%E5%B7%A1%E6%BC%94.png",
        "cc": "CC BY 4.0"
    },
    {
        "names": [
            "Any.C",
            "鄭安偉",
            "安偉"
        ],
        "image_name": "安偉.png",
        "reference": "This image is provided by JM Liu, 安偉 article, source: Wikipedia",
        "article_url": "https://zh.wikipedia.org/wiki/%E5%AE%89%E5%81%89_(%E6%AD%8C%E6%89%8B)",
        "image_url": "https://zh.wikipedia.org/wiki/%E5%AE%89%E5%81%89_(%E6%AD%8C%E6%89%8B)#/media/File:%E5%8D%97%E9%96%8B%E6%A0%A1%E5%94%B1.jpg",
        "cc": "CC BY-SA 4.0"
    },
    {
        "names": [
            "五角",
            "50 Cent"
        ],
        "image_name": "50 Cent.png",
        "reference": "This image is provided by Alex Const, 50 Cent article, source: Wikipedia",
        "article_url": "https://zh.wikipedia.org/wiki/50_Cent",
        "image_url": "https://zh.wikipedia.org/wiki/50_Cent#/media/File:50_cent_in_concert.jpg",
        "cc": "CC BY 2.0"
    },
    {
        "names": [
            "MIKHAÉL",
            "瑞彥·迷嘉爾"
        ],
        "image_name": "-",
        "reference": "瑞彥·迷嘉爾 article, source: Wikipedia",
        "article_url": "https://zh.wikipedia.org/wiki/%E7%91%9E%E5%BD%A6%C2%B7%E8%BF%B7%E5%98%89%E5%B0%94",
        "image_url": "-",
        "cc": "-"
    },
    {
        "names": [
            "Clay Aiken",
            "克萊·艾肯"
        ],
        "image_name": "克萊·艾肯.png",
        "reference": "This image is provided by mystuff1, 克萊·艾肯 article, source: Wikipedia",
        "article_url": "https://zh.wikipedia.org/wiki/%E5%85%8B%E8%90%8A%C2%B7%E8%89%BE%E8%82%AF",
        "image_url": "https://zh.wikipedia.org/wiki/%E5%85%8B%E8%90%8A%C2%B7%E8%89%BE%E8%82%AF#/media/File:Clay_Aiken_Merrillville_05-08-23.jpg",
        "cc": "CC BY-SA 2.0"
    }
]